lofar_parameterset/__init__.py
lofar_parameterset/_version.py
lofar_parameterset/parameterset.py
lofar_parameterset-1.1.dist-info/licenses/LICENSE
lofar_parameterset-1.1.dist-info/METADATA
lofar_parameterset-1.1.dist-info/WHEEL
lofar_parameterset-1.1.dist-info/top_level.txt
lofar_parameterset-1.1.dist-info/RECORD
