Metadata-Version: 2.4
Name: lofar-parameterset
Version: 1.1
Summary: Minimal Python implementation of the LOFAR ParameterSet
Author-email: Jan David Mol <mol@astron.nl>
License: GPL-3.0-or-later
Project-URL: repository, https://git.astron.nl/lofar2.0/lofar_pyparameterset
Keywords: LOFAR,ParameterSet
Classifier: Development Status :: 5 - Production/Stable
Classifier: Intended Audience :: Developers
Classifier: Intended Audience :: Science/Research
Classifier: License :: OSI Approved :: GNU General Public License v3 or later (GPLv3+)
Classifier: Operating System :: OS Independent
Classifier: Programming Language :: Python :: 3
Classifier: Topic :: Scientific/Engineering
Classifier: Topic :: Scientific/Engineering :: Astronomy
Requires-Python: >=3.10
License-File: LICENSE
Dynamic: license-file
